{"ID":"6a269319-72fe-4b9b-a4e4-79ce13c4347a","Version":"2.3.4","Name":"watchLayer","Content":{"Content":{"Animation":{"Duration":0,"Speed":1,"Timelines":[],"ctype":"TimelineActionData"},"AnimationList":[],"ObjectData":{"Tag":64,"Children":[{"FontSize":14,"ButtonText":"","TextColor":{"R":65,"G":65,"B":70},"PressedFileData":{"Type":"PlistSubImage","Path":"btn_watch.png","Plist":"common/watchLayer/watchLayer.plist"},"NormalFileData":{"Type":"PlistSubImage","Path":"btn_watch.png","Plist":"common/watchLayer/watchLayer.plist"},"Scale9Enable":true,"Scale9OriginX":15,"Scale9OriginY":11,"Scale9Width":40,"Scale9Height":45,"OutlineColor":{"G":0,"B":0},"ShadowColor":{"R":110,"G":110,"B":110},"ShadowOffsetX":2,"ShadowOffsetY":-2,"TouchEnable":true,"AnchorPoint":{"ScaleX":0.5,"ScaleY":0.5},"Position":{"X":1024,"Y":360},"Scale":{"ScaleX":1,"ScaleY":1},"CColor":{},"IconVisible":false,"PositionPercentXEnabled":true,"PositionPercentYEnabled":true,"PrePosition":{"X":0.8,"Y":0.5},"PreSize":{"X":0.0547,"Y":0.0931},"LeftMargin":989,"RightMargin":221,"TopMargin":326.5,"BottomMargin":326.5,"Tag":65,"ActionTag":440797023,"Size":{"X":70,"Y":67},"Name":"btn_watch_1","ctype":"ButtonObjectData"},{"FontSize":14,"ButtonText":"","TextColor":{"R":65,"G":65,"B":70},"PressedFileData":{"Type":"PlistSubImage","Path":"btn_watch.png","Plist":"common/watchLayer/watchLayer.plist"},"NormalFileData":{"Type":"PlistSubImage","Path":"btn_watch.png","Plist":"common/watchLayer/watchLayer.plist"},"Scale9Enable":true,"Scale9OriginX":15,"Scale9OriginY":11,"Scale9Width":40,"Scale9Height":45,"OutlineColor":{"G":0,"B":0},"ShadowColor":{"R":110,"G":110,"B":110},"ShadowOffsetX":2,"ShadowOffsetY":-2,"TouchEnable":true,"AnchorPoint":{"ScaleX":0.5,"ScaleY":0.5},"Position":{"X":640,"Y":576},"Scale":{"ScaleX":1,"ScaleY":1},"CColor":{},"IconVisible":false,"PositionPercentXEnabled":true,"PositionPercentYEnabled":true,"PrePosition":{"X":0.5,"Y":0.8},"PreSize":{"X":0.0547,"Y":0.0931},"LeftMargin":605,"RightMargin":605,"TopMargin":110.5,"BottomMargin":542.5,"Tag":66,"ActionTag":-1646924945,"Size":{"X":70,"Y":67},"Name":"btn_watch_2","ctype":"ButtonObjectData"},{"FontSize":14,"ButtonText":"","TextColor":{"R":65,"G":65,"B":70},"PressedFileData":{"Type":"PlistSubImage","Path":"btn_watch.png","Plist":"common/watchLayer/watchLayer.plist"},"NormalFileData":{"Type":"PlistSubImage","Path":"btn_watch.png","Plist":"common/watchLayer/watchLayer.plist"},"Scale9Enable":true,"Scale9OriginX":15,"Scale9OriginY":11,"Scale9Width":40,"Scale9Height":45,"OutlineColor":{"G":0,"B":0},"ShadowColor":{"R":110,"G":110,"B":110},"ShadowOffsetX":2,"ShadowOffsetY":-2,"TouchEnable":true,"AnchorPoint":{"ScaleX":0.5,"ScaleY":0.5},"Position":{"X":256,"Y":360},"Scale":{"ScaleX":1,"ScaleY":1},"CColor":{},"IconVisible":false,"PositionPercentXEnabled":true,"PositionPercentYEnabled":true,"PrePosition":{"X":0.2,"Y":0.5},"PreSize":{"X":0.0547,"Y":0.0931},"LeftMargin":221,"RightMargin":989,"TopMargin":326.5,"BottomMargin":326.5,"Tag":67,"ActionTag":-24004611,"Size":{"X":70,"Y":67},"Name":"btn_watch_3","ctype":"ButtonObjectData"},{"FontSize":14,"ButtonText":"","TextColor":{"R":65,"G":65,"B":70},"PressedFileData":{"Type":"PlistSubImage","Path":"btn_look_deep.png","Plist":"common/watchLayer/watchLayer.plist"},"NormalFileData":{"Type":"PlistSubImage","Path":"btn_look.png","Plist":"common/watchLayer/watchLayer.plist"},"Scale9Enable":true,"Scale9OriginX":15,"Scale9OriginY":11,"Scale9Width":40,"Scale9Height":45,"OutlineColor":{"G":0,"B":0},"ShadowColor":{"R":110,"G":110,"B":110},"ShadowOffsetX":2,"ShadowOffsetY":-2,"TouchEnable":true,"AnchorPoint":{"ScaleX":0.5,"ScaleY":0.5},"Position":{"X":1023.2319,"Y":664.488},"Scale":{"ScaleX":1,"ScaleY":1},"CColor":{},"IconVisible":false,"PositionPercentXEnabled":true,"PositionPercentYEnabled":true,"PrePosition":{"X":0.7994,"Y":0.9229},"PreSize":{"X":0.0547,"Y":0.0931},"LeftMargin":988.2319,"RightMargin":221.7681,"TopMargin":22.012,"BottomMargin":630.988,"Tag":711,"ActionTag":266380109,"Size":{"X":70,"Y":67},"Name":"btn_watch_player","ctype":"ButtonObjectData"},{"IsBounceEnabled":true,"InnerNodeSize":{"Width":204,"Height":450},"ScrollDirectionType":"Vertical","ClipAble":true,"BackColorAlpha":102,"FileData":{"Type":"PlistSubImage","Path":"watchPlayerBg.png","Plist":"common/watchLayer/watchLayer.plist"},"ComboBoxIndex":1,"SingleColor":{"G":150,"B":100},"FirstColor":{"G":150,"B":100},"EndColor":{},"ColorVector":{"ScaleY":1},"Scale9OriginX":67,"Scale9OriginY":148,"Scale9Width":70,"Scale9Height":154,"TouchEnable":true,"AnchorPoint":{"ScaleX":0.5,"ScaleY":1},"Position":{"X":1027.7656,"Y":621.6885},"Scale":{"ScaleX":1,"ScaleY":1},"CColor":{},"IconVisible":false,"PrePosition":{"X":0.8029,"Y":0.8635},"PreSize":{"X":0.1594,"Y":0.625},"LeftMargin":925.7656,"RightMargin":150.2344,"TopMargin":98.3115,"BottomMargin":171.6885,"Tag":395,"ActionTag":1846966103,"Size":{"X":204,"Y":450},"Name":"list_watch_player","ctype":"ScrollViewObjectData"}],"Size":{"X":1280,"Y":720},"Name":"Layer","ctype":"LayerObjectData"},"UsedResources":["watchLayer.plist","watchLayer.png"],"ctype":"GameFileData"}},"Type":"Layer"}