{"ID":"7d3e8a91-c76c-4a3a-8474-f730f850b921","Version":"2.3.4","Name":"TH_ChooseFastGame","Content":{"Content":{"Animation":{"Duration":0,"Speed":1,"Timelines":[],"ctype":"TimelineActionData"},"AnimationList":[],"ObjectData":{"Tag":108,"Children":[{"ClipAble":false,"BackColorAlpha":178,"ComboBoxIndex":1,"SingleColor":{"R":0,"G":0,"B":0},"FirstColor":{"R":150,"G":200},"EndColor":{},"ColorVector":{"ScaleY":1},"Scale9Width":1,"Scale9Height":1,"TouchEnable":true,"StretchWidthEnable":true,"StretchHeightEnable":true,"AnchorPoint":{"ScaleX":0.5,"ScaleY":0.5},"Position":{"X":640,"Y":360},"Scale":{"ScaleX":1,"ScaleY":1},"CColor":{},"IconVisible":false,"PrePosition":{"X":0.5,"Y":0.5},"PreSize":{"X":1,"Y":1},"HorizontalEdge":"LeftEdge","VerticalEdge":"TopEdge","Tag":117,"ActionTag":-1217493343,"Size":{"X":1280,"Y":720},"Name":"maskbg","ctype":"PanelObjectData"},{"ClipAble":false,"BackColorAlpha":102,"FileData":{"Type":"PlistSubImage","Path":"Bg888548.png","Plist":"lobby/TeaHouse/TH_BlackListPanel/TeaHouse_new_BlackList.plist"},"SingleColor":{"R":150,"G":200},"FirstColor":{"R":150,"G":200},"EndColor":{},"ColorVector":{"ScaleY":1},"Scale9Enable":true,"Scale9OriginX":204,"Scale9OriginY":141,"Scale9Width":480,"Scale9Height":266,"TouchEnable":true,"AnchorPoint":{"ScaleX":0.5,"ScaleY":0.5},"Position":{"X":640,"Y":346.5},"Scale":{"ScaleX":1,"ScaleY":1},"CColor":{},"IconVisible":false,"PositionPercentXEnabled":true,"PrePosition":{"X":0.5,"Y":0.4812},"PreSize":{"X":0.8984,"Y":0.9444},"VerticalEdge":"BottomEdge","LeftMargin":65,"RightMargin":65,"TopMargin":33.5,"BottomMargin":6.5,"Tag":109,"Children":[{"FontSize":14,"ButtonText":"","TextColor":{"R":65,"G":65,"B":70},"DisabledFileData":{"Type":"PlistSubImage","Path":"common_btn_close_deep.png","Plist":"common/bnts/common_new_btns.plist"},"PressedFileData":{"Type":"PlistSubImage","Path":"common_btn_close_deep.png","Plist":"common/bnts/common_new_btns.plist"},"NormalFileData":{"Type":"PlistSubImage","Path":"common_btn_close.png","Plist":"common/bnts/common_new_btns.plist"},"Scale9OriginX":15,"Scale9OriginY":11,"Scale9Width":26,"Scale9Height":36,"OutlineColor":{"G":0,"B":0},"ShadowColor":{"R":110,"G":110,"B":110},"ShadowOffsetX":2,"ShadowOffsetY":-2,"TouchEnable":true,"AnchorPoint":{"ScaleX":0.5,"ScaleY":0.5},"Position":{"X":1140.5012,"Y":665.002},"Scale":{"ScaleX":1,"ScaleY":1},"CColor":{},"IconVisible":false,"PrePosition":{"X":0.9917,"Y":0.9779},"PreSize":{"X":0.0487,"Y":0.0853},"HorizontalEdge":"RightEdge","VerticalEdge":"TopEdge","LeftMargin":1112.5012,"RightMargin":-18.5012,"TopMargin":-14.002,"BottomMargin":636.002,"Tag":141,"ActionTag":-2084451372,"Size":{"X":56,"Y":58},"Name":"CloseButton","ctype":"ButtonObjectData"},{"FileData":{"Type":"PlistSubImage","Path":"chooseGameTitle.png","Plist":"lobby/TeaHouse/TH_MenuBlocks/TH_ChooseFastGame.plist"},"BlendFunc":{"Src":1,"Dst":771},"AnchorPoint":{"ScaleX":0.5,"ScaleY":0.5},"Position":{"X":575,"Y":650.005},"Scale":{"ScaleX":1,"ScaleY":1},"CColor":{},"IconVisible":false,"PositionPercentXEnabled":true,"PrePosition":{"X":0.5,"Y":0.9559},"PreSize":{"X":0.2157,"Y":0.1074},"VerticalEdge":"TopEdge","LeftMargin":451,"RightMargin":451,"TopMargin":-6.505,"BottomMargin":613.505,"Tag":110,"ActionTag":612474145,"Size":{"X":248,"Y":73},"Name":"Title","ctype":"SpriteObjectData"},{"IsBounceEnabled":true,"InnerNodeSize":{"Width":1162,"Height":581},"ScrollDirectionType":"Vertical","ClipAble":true,"BackColorAlpha":102,"SingleColor":{"G":150,"B":100},"FirstColor":{"G":150,"B":100},"EndColor":{},"ColorVector":{"ScaleY":1},"Scale9Width":1,"Scale9Height":1,"TouchEnable":true,"AnchorPoint":{"ScaleX":0.5,"ScaleY":0.5},"Position":{"X":574,"Y":317.968},"Scale":{"ScaleX":1,"ScaleY":1},"CColor":{},"IconVisible":false,"PositionPercentXEnabled":true,"PositionPercentYEnabled":true,"PrePosition":{"X":0.4991,"Y":0.4676},"PreSize":{"X":0.9626,"Y":0.7985},"LeftMargin":20.5,"RightMargin":22.5,"TopMargin":90.532,"BottomMargin":46.468,"Tag":34,"ActionTag":411136637,"Size":{"X":1107,"Y":543},"Name":"ScrollView","ctype":"ScrollViewObjectData"}],"ActionTag":1664355676,"Size":{"X":1150,"Y":680},"Name":"contentPanel","ctype":"PanelObjectData"},{"ClipAble":false,"BackColorAlpha":66,"SingleColor":{"R":150,"G":200},"FirstColor":{"R":150,"G":200},"EndColor":{},"ColorVector":{"ScaleY":1},"Scale9Enable":true,"Scale9OriginX":-30,"Scale9OriginY":-30,"Scale9Width":60,"Scale9Height":60,"TouchEnable":true,"AnchorPoint":{"ScaleY":0.5},"Position":{"X":51.04,"Y":-159.4415},"Scale":{"ScaleX":1,"ScaleY":1},"CColor":{},"IconVisible":false,"PrePosition":{"X":0.0399,"Y":-0.2214},"PreSize":{"X":0.4274,"Y":0.1097},"LeftMargin":51.04,"RightMargin":681.8831,"TopMargin":839.9415,"BottomMargin":-198.9415,"Tag":83,"Children":[{"FileData":{"Type":"PlistSubImage","Path":"TH_chooseGameItem.png","Plist":"lobby/TeaHouse/TH_MenuBlocks/TH_ChooseFastGame.plist"},"Scale9OriginX":185,"Scale9OriginY":30,"Scale9Width":192,"Scale9Height":31,"AnchorPoint":{"ScaleX":0.5,"ScaleY":0.5},"Position":{"X":273.5385,"Y":39.5},"Scale":{"ScaleX":1,"ScaleY":1},"CColor":{},"IconVisible":false,"PositionPercentXEnabled":true,"PositionPercentYEnabled":true,"PrePosition":{"X":0.5,"Y":0.5},"PercentWidthEnable":true,"PercentHeightEnable":true,"PercentWidthEnabled":true,"PercentHeightEnabled":true,"PreSize":{"X":1,"Y":1},"Tag":134,"ActionTag":880287893,"Size":{"X":547.0769,"Y":79},"Name":"bg_nor","ctype":"ImageViewObjectData"},{"FileData":{"Type":"PlistSubImage","Path":"TH_chooseGameItem_sel.png","Plist":"lobby/TeaHouse/TH_MenuBlocks/TH_ChooseFastGame.plist"},"Scale9OriginX":185,"Scale9OriginY":30,"Scale9Width":192,"Scale9Height":31,"AnchorPoint":{"ScaleX":0.5,"ScaleY":0.5},"Position":{"X":273.5385,"Y":39.5},"Scale":{"ScaleX":1,"ScaleY":1},"CColor":{},"IconVisible":false,"PositionPercentXEnabled":true,"PositionPercentYEnabled":true,"PrePosition":{"X":0.5,"Y":0.5},"PercentWidthEnable":true,"PercentHeightEnable":true,"PercentWidthEnabled":true,"PercentHeightEnabled":true,"PreSize":{"X":1,"Y":1},"Tag":135,"ActionTag":1475704550,"Size":{"X":547.0769,"Y":79},"Name":"bg_sel","ctype":"ImageViewObjectData"},{"FileData":{"Type":"Default","Path":"Default/ImageFile.png","Plist":""},"Scale9Width":46,"Scale9Height":46,"AnchorPoint":{"ScaleX":0.5,"ScaleY":0.5},"Position":{"X":38.0341,"Y":39.2881},"Scale":{"ScaleX":1,"ScaleY":1},"CColor":{},"IconVisible":false,"PrePosition":{"X":0.0695,"Y":0.4973},"PreSize":{"X":0.0841,"Y":0.5823},"LeftMargin":15.0341,"RightMargin":486.0428,"TopMargin":16.7119,"BottomMargin":16.2881,"Tag":84,"ActionTag":-968561941,"Size":{"X":46,"Y":46},"Name":"gameIcon","ctype":"ImageViewObjectData"},{"IsCustomSize":true,"FontSize":24,"LabelText":"Text Label","VerticalAlignmentType":"VT_Center","OutlineColor":{"G":0,"B":0},"ShadowColor":{"R":110,"G":110,"B":110},"ShadowOffsetX":2,"ShadowOffsetY":-2,"AnchorPoint":{"ScaleY":0.5},"Position":{"X":80.65,"Y":53.4031},"Scale":{"ScaleX":1,"ScaleY":1},"CColor":{"R":185,"G":125,"B":85},"IconVisible":false,"PrePosition":{"X":0.1474,"Y":0.676},"PreSize":{"X":0.3561,"Y":0.3797},"LeftMargin":80.65,"RightMargin":271.5925,"TopMargin":10.5969,"BottomMargin":38.4031,"Tag":85,"ActionTag":698689162,"Size":{"X":194.8344,"Y":30},"Name":"gameSubName","ctype":"TextObjectData"},{"IsCustomSize":true,"FontSize":22,"LabelText":"应城卡五星 2人16局","VerticalAlignmentType":"VT_Center","OutlineColor":{"G":0,"B":0},"ShadowColor":{"R":110,"G":110,"B":110},"ShadowOffsetX":2,"ShadowOffsetY":-2,"AnchorPoint":{"ScaleY":0.5},"Position":{"X":80.65,"Y":21.8504},"Scale":{"ScaleX":1,"ScaleY":1},"CColor":{"R":211,"G":58,"B":37},"IconVisible":false,"PrePosition":{"X":0.1474,"Y":0.2766},"PreSize":{"X":0.4112,"Y":0.3797},"LeftMargin":80.65,"RightMargin":241.4614,"TopMargin":42.1496,"BottomMargin":6.8504,"Tag":86,"ActionTag":1859470557,"Size":{"X":224.9655,"Y":30},"Name":"gamebigname","ctype":"TextObjectData"},{"FontSize":14,"ButtonText":"","TextColor":{"R":65,"G":65,"B":70},"DisabledFileData":{"Type":"Default","Path":"Default/Button_Disable.png","Plist":""},"PressedFileData":{"Type":"PlistSubImage","Path":"TH_GameFastbtn_deep.png","Plist":"lobby/TeaHouse/TH_MenuBlocks/TH_ChooseFastGame.plist"},"NormalFileData":{"Type":"PlistSubImage","Path":"TH_GameFastbtn.png","Plist":"lobby/TeaHouse/TH_MenuBlocks/TH_ChooseFastGame.plist"},"Scale9Enable":true,"Scale9OriginX":15,"Scale9OriginY":11,"Scale9Width":92,"Scale9Height":27,"OutlineColor":{"G":0,"B":0},"ShadowColor":{"R":110,"G":110,"B":110},"ShadowOffsetX":2,"ShadowOffsetY":-2,"TouchEnable":true,"AnchorPoint":{"ScaleX":0.5,"ScaleY":0.5},"Position":{"X":489.1805,"Y":37.0176},"Scale":{"ScaleX":0.8,"ScaleY":0.8},"CColor":{},"IconVisible":false,"PositionPercentYEnabled":true,"PrePosition":{"X":0.8942,"Y":0.4686},"PreSize":{"X":0.223,"Y":0.6203},"HorizontalEdge":"RightEdge","LeftMargin":428.1805,"RightMargin":-3.1036,"TopMargin":17.4824,"BottomMargin":12.5176,"Tag":87,"ActionTag":-1155550943,"Size":{"X":122,"Y":49},"Name":"btn_fast","ctype":"ButtonObjectData"},{"ClipAble":false,"BackColorAlpha":102,"SingleColor":{"R":150,"G":200},"FirstColor":{"R":150,"G":200},"EndColor":{},"ColorVector":{"ScaleY":1},"Scale9Width":1,"Scale9Height":1,"TouchEnable":true,"AnchorPoint":{},"Position":{"X":271.3358,"Y":0},"Scale":{"ScaleX":1,"ScaleY":1},"CColor":{},"IconVisible":false,"PrePosition":{"X":0.496,"Y":0},"PercentHeightEnable":true,"PercentHeightEnabled":true,"PreSize":{"X":0.3656,"Y":1},"LeftMargin":271.3358,"RightMargin":75.7411,"Tag":358,"Children":[{"IsCustomSize":true,"FontSize":24,"LabelText":"桌数：","VerticalAlignmentType":"VT_Center","OutlineColor":{"G":0,"B":0},"ShadowColor":{"R":110,"G":110,"B":110},"ShadowOffsetX":2,"ShadowOffsetY":-2,"AnchorPoint":{"ScaleY":0.5},"Position":{"X":55.4888,"Y":53.4002},"Scale":{"ScaleX":1,"ScaleY":1},"CColor":{"R":185,"G":125,"B":85},"IconVisible":false,"PrePosition":{"X":0.2774,"Y":0.676},"PreSize":{"X":0.3879,"Y":0.3797},"LeftMargin":55.4888,"RightMargin":66.9329,"TopMargin":10.5998,"BottomMargin":38.4002,"Tag":354,"ActionTag":742082431,"Size":{"X":77.5783,"Y":30},"Name":"fulltableCount_font","ctype":"TextObjectData"},{"IsCustomSize":true,"FontSize":24,"LabelText":"1000","VerticalAlignmentType":"VT_Center","OutlineColor":{"G":0,"B":0},"ShadowColor":{"R":110,"G":110,"B":110},"ShadowOffsetX":2,"ShadowOffsetY":-2,"AnchorPoint":{"ScaleY":0.5},"Position":{"X":112.4176,"Y":53.4003},"Scale":{"ScaleX":1,"ScaleY":1},"CColor":{"R":211,"G":58,"B":37},"IconVisible":false,"PrePosition":{"X":0.5621,"Y":0.676},"PreSize":{"X":0.3604,"Y":0.3797},"LeftMargin":112.4176,"RightMargin":15.4996,"TopMargin":10.5997,"BottomMargin":38.4003,"Tag":355,"ActionTag":1030888649,"Size":{"X":72.0828,"Y":30},"Name":"fulltableCount","ctype":"TextObjectData"},{"IsCustomSize":true,"FontSize":24,"LabelText":"匹配中：","VerticalAlignmentType":"VT_Center","OutlineColor":{"G":0,"B":0},"ShadowColor":{"R":110,"G":110,"B":110},"ShadowOffsetX":2,"ShadowOffsetY":-2,"AnchorPoint":{"ScaleY":0.5},"Position":{"X":31.5789,"Y":21.8502},"Scale":{"ScaleX":1,"ScaleY":1},"CColor":{"R":185,"G":125,"B":85},"IconVisible":false,"PrePosition":{"X":0.1579,"Y":0.2766},"PreSize":{"X":0.5348,"Y":0.3797},"LeftMargin":31.5789,"RightMargin":61.4654,"TopMargin":42.1498,"BottomMargin":6.8502,"Tag":356,"ActionTag":-970507388,"Size":{"X":106.9557,"Y":30},"Name":"matchCount_font","ctype":"TextObjectData"},{"IsCustomSize":true,"FontSize":24,"LabelText":"1000","VerticalAlignmentType":"VT_Center","OutlineColor":{"G":0,"B":0},"ShadowColor":{"R":110,"G":110,"B":110},"ShadowOffsetX":2,"ShadowOffsetY":-2,"AnchorPoint":{"ScaleY":0.5},"Position":{"X":112.507,"Y":21.8503},"Scale":{"ScaleX":1,"ScaleY":1},"CColor":{"R":211,"G":58,"B":37},"IconVisible":false,"PrePosition":{"X":0.5625,"Y":0.2766},"PreSize":{"X":0.319,"Y":0.3797},"LeftMargin":112.507,"RightMargin":23.6902,"TopMargin":42.1497,"BottomMargin":6.8503,"Tag":357,"ActionTag":402862970,"Size":{"X":63.8027,"Y":30},"Name":"matchCount","ctype":"TextObjectData"}],"ActionTag":1595486554,"Size":{"X":200,"Y":79},"Name":"tableMatchLayout","ctype":"PanelObjectData"}],"ActionTag":-175278673,"Size":{"X":547.0769,"Y":79},"Name":"TH_gameChooseitem","ctype":"PanelObjectData"}],"Size":{"X":1280,"Y":720},"Name":"Layer","ctype":"LayerObjectData"},"UsedResources":["../../../common/bnts/common_new_btns.plist","../../../common/bnts/common_new_btns.png","../../../Default/Button_Disable.png","../../../Default/ImageFile.png","../TH_BlackListPanel/TeaHouse_new_BlackList.plist","../TH_BlackListPanel/TeaHouse_new_BlackList.png","TH_ChooseFastGame.plist","TH_ChooseFastGame.png"],"ctype":"GameFileData"}},"Type":"Layer"}